CHANGELOG.md
LICENSE
MANIFEST.in
README.md
setup.py
ekman/__init__.py
ekman/atmos.py
ekman/conf.py
ekman/ocean.py
ekman/seaice.py
ekman.egg-info/PKG-INFO
ekman.egg-info/SOURCES.txt
ekman.egg-info/dependency_links.txt
ekman.egg-info/not-zip-safe
ekman.egg-info/requires.txt
ekman.egg-info/top_level.txt