Metadata-Version: 1.2
Name: ekman
Version: 0.1.1a1
Summary:  A Python package to postprocess, data analyze and visualize model outputs
Home-page: https://github.com/uesleisutil
Author: Ueslei Adriano Sutil
License: BSD-3-Clause
Platform: UNKNOWN
Classifier: License :: OSI Approved :: BSD License
Classifier: Intended Audience :: Developers
Classifier: Intended Audience :: Science/Research
Classifier: Natural Language :: English
Classifier: Programming Language :: Python :: 3
Requires-Python: >=3
